[{"issue":{"state":"closed","id":3570930923,"nodeId":"I_kwDOQFxmOs7U2BTr","url":"https://github.com/cennso/cennso-website/issues/48","title":"Accessibility issue: Elements must meet minimum color contrast ratio thresholds on /"},"findings":[]},{"issue":{"state":"closed","id":3570931118,"nodeId":"I_kwDOQFxmOs7U2BWu","url":"https://github.com/cennso/cennso-website/issues/49","title":"Accessibility issue: Main landmark should not be contained in another landmark on /"},"findings":[]},{"issue":{"state":"closed","id":3570931520,"nodeId":"I_kwDOQFxmOs7U2BdA","url":"https://github.com/cennso/cennso-website/issues/50","title":"Accessibility issue: Document should not have more than one main landmark on /"},"findings":[]},{"issue":{"state":"closed","id":3570931836,"nodeId":"I_kwDOQFxmOs7U2Bh8","url":"https://github.com/cennso/cennso-website/issues/51","title":"Accessibility issue: Landmarks should have a unique role or role/label/title (i.e. accessible name) combination on /"},"findings":[]},{"issue":{"state":"closed","id":3570932027,"nodeId":"I_kwDOQFxmOs7U2Bk7","url":"https://github.com/cennso/cennso-website/issues/52","title":"Accessibility issue: Interactive controls must not be nested on /"},"findings":[]},{"issue":{"state":"closed","id":3570932531,"nodeId":"I_kwDOQFxmOs7U2Bsz","url":"https://github.com/cennso/cennso-website/issues/53","title":"Accessibility issue: All page content should be contained by landmarks on /"},"findings":[]},{"issue":{"state":"closed","id":3570932686,"nodeId":"I_kwDOQFxmOs7U2BvO","url":"https://github.com/cennso/cennso-website/issues/54","title":"Accessibility issue: Elements must meet minimum color contrast ratio thresholds on /success-stories"},"findings":[]},{"issue":{"state":"closed","id":3570932885,"nodeId":"I_kwDOQFxmOs7U2ByV","url":"https://github.com/cennso/cennso-website/issues/55","title":"Accessibility issue: Heading levels should only increase by one on /success-stories"},"findings":[]},{"issue":{"state":"closed","id":3570933060,"nodeId":"I_kwDOQFxmOs7U2B1E","url":"https://github.com/cennso/cennso-website/issues/56","title":"Accessibility issue: Main landmark should not be contained in another landmark on /success-stories"},"findings":[]},{"issue":{"state":"closed","id":3570933264,"nodeId":"I_kwDOQFxmOs7U2B4Q","url":"https://github.com/cennso/cennso-website/issues/57","title":"Accessibility issue: Document should not have more than one main landmark on /success-stories"},"findings":[]},{"issue":{"state":"closed","id":3570933450,"nodeId":"I_kwDOQFxmOs7U2B7K","url":"https://github.com/cennso/cennso-website/issues/58","title":"Accessibility issue: Landmarks should have a unique role or role/label/title (i.e. accessible name) combination on /success-stories"},"findings":[]},{"issue":{"state":"closed","id":3570933629,"nodeId":"I_kwDOQFxmOs7U2B99","url":"https://github.com/cennso/cennso-website/issues/59","title":"Accessibility issue: Interactive controls must not be nested on /success-stories"},"findings":[]},{"issue":{"state":"closed","id":3570934112,"nodeId":"I_kwDOQFxmOs7U2CFg","url":"https://github.com/cennso/cennso-website/issues/60","title":"Accessibility issue: All page content should be contained by landmarks on /success-stories"},"findings":[]},{"issue":{"state":"closed","id":3570934422,"nodeId":"I_kwDOQFxmOs7U2CKW","url":"https://github.com/cennso/cennso-website/issues/61","title":"Accessibility issue: Aria hidden element must not be focusable or contain focusable elements on /contact"},"findings":[]},{"issue":{"state":"closed","id":3570934628,"nodeId":"I_kwDOQFxmOs7U2CNk","url":"https://github.com/cennso/cennso-website/issues/62","title":"Accessibility issue: Autocomplete attribute must be used correctly on /contact"},"findings":[]},{"issue":{"state":"closed","id":3570934799,"nodeId":"I_kwDOQFxmOs7U2CQP","url":"https://github.com/cennso/cennso-website/issues/63","title":"Accessibility issue: Elements must meet minimum color contrast ratio thresholds on /contact"},"findings":[]},{"issue":{"state":"closed","id":3570934993,"nodeId":"I_kwDOQFxmOs7U2CTR","url":"https://github.com/cennso/cennso-website/issues/64","title":"Accessibility issue: Main landmark should not be contained in another landmark on /contact"},"findings":[]},{"issue":{"state":"closed","id":3570935165,"nodeId":"I_kwDOQFxmOs7U2CV9","url":"https://github.com/cennso/cennso-website/issues/65","title":"Accessibility issue: Document should not have more than one main landmark on /contact"},"findings":[]},{"issue":{"state":"closed","id":3570935371,"nodeId":"I_kwDOQFxmOs7U2CZL","url":"https://github.com/cennso/cennso-website/issues/66","title":"Accessibility issue: Landmarks should have a unique role or role/label/title (i.e. accessible name) combination on /contact"},"findings":[]},{"issue":{"state":"closed","id":3570935704,"nodeId":"I_kwDOQFxmOs7U2CeY","url":"https://github.com/cennso/cennso-website/issues/67","title":"Accessibility issue: Interactive controls must not be nested on /contact"},"findings":[]},{"issue":{"state":"closed","id":3570935897,"nodeId":"I_kwDOQFxmOs7U2ChZ","url":"https://github.com/cennso/cennso-website/issues/68","title":"Accessibility issue: All page content should be contained by landmarks on /contact"},"findings":[]},{"issue":{"state":"closed","id":3570936115,"nodeId":"I_kwDOQFxmOs7U2Ckz","url":"https://github.com/cennso/cennso-website/issues/69","title":"Accessibility issue: Heading levels should only increase by one on /about"},"findings":[]},{"issue":{"state":"closed","id":3570936269,"nodeId":"I_kwDOQFxmOs7U2CnN","url":"https://github.com/cennso/cennso-website/issues/70","title":"Accessibility issue: Main landmark should not be contained in another landmark on /about"},"findings":[]},{"issue":{"state":"closed","id":3570936453,"nodeId":"I_kwDOQFxmOs7U2CqF","url":"https://github.com/cennso/cennso-website/issues/71","title":"Accessibility issue: Document should not have more than one main landmark on /about"},"findings":[]},{"issue":{"state":"closed","id":3570936606,"nodeId":"I_kwDOQFxmOs7U2Cse","url":"https://github.com/cennso/cennso-website/issues/72","title":"Accessibility issue: Landmarks should have a unique role or role/label/title (i.e. accessible name) combination on /about"},"findings":[]},{"issue":{"state":"closed","id":3570936820,"nodeId":"I_kwDOQFxmOs7U2Cv0","url":"https://github.com/cennso/cennso-website/issues/73","title":"Accessibility issue: Interactive controls must not be nested on /about"},"findings":[]},{"issue":{"state":"closed","id":3570937035,"nodeId":"I_kwDOQFxmOs7U2CzL","url":"https://github.com/cennso/cennso-website/issues/74","title":"Accessibility issue: All page content should be contained by landmarks on /about"},"findings":[]},{"issue":{"state":"closed","id":3570937240,"nodeId":"I_kwDOQFxmOs7U2C2Y","url":"https://github.com/cennso/cennso-website/issues/75","title":"Accessibility issue: Heading levels should only increase by one on /blog"},"findings":[]},{"issue":{"state":"closed","id":3570937444,"nodeId":"I_kwDOQFxmOs7U2C5k","url":"https://github.com/cennso/cennso-website/issues/76","title":"Accessibility issue: Main landmark should not be contained in another landmark on /blog"},"findings":[]},{"issue":{"state":"closed","id":3570937634,"nodeId":"I_kwDOQFxmOs7U2C8i","url":"https://github.com/cennso/cennso-website/issues/77","title":"Accessibility issue: Document should not have more than one main landmark on /blog"},"findings":[]},{"issue":{"state":"closed","id":3570937831,"nodeId":"I_kwDOQFxmOs7U2C_n","url":"https://github.com/cennso/cennso-website/issues/78","title":"Accessibility issue: Landmarks should have a unique role or role/label/title (i.e. accessible name) combination on /blog"},"findings":[]},{"issue":{"state":"closed","id":3570938032,"nodeId":"I_kwDOQFxmOs7U2DCw","url":"https://github.com/cennso/cennso-website/issues/79","title":"Accessibility issue: Interactive controls must not be nested on /blog"},"findings":[]},{"issue":{"state":"closed","id":3570938207,"nodeId":"I_kwDOQFxmOs7U2DFf","url":"https://github.com/cennso/cennso-website/issues/80","title":"Accessibility issue: All page content should be contained by landmarks on /blog"},"findings":[]},{"issue":{"state":"closed","id":3570938409,"nodeId":"I_kwDOQFxmOs7U2DIp","url":"https://github.com/cennso/cennso-website/issues/81","title":"Accessibility issue: Heading levels should only increase by one on /solutions"},"findings":[]},{"issue":{"state":"closed","id":3570938602,"nodeId":"I_kwDOQFxmOs7U2DLq","url":"https://github.com/cennso/cennso-website/issues/82","title":"Accessibility issue: Main landmark should not be contained in another landmark on /solutions"},"findings":[]},{"issue":{"state":"closed","id":3570938798,"nodeId":"I_kwDOQFxmOs7U2DOu","url":"https://github.com/cennso/cennso-website/issues/83","title":"Accessibility issue: Document should not have more than one main landmark on /solutions"},"findings":[]},{"issue":{"state":"closed","id":3570938993,"nodeId":"I_kwDOQFxmOs7U2DRx","url":"https://github.com/cennso/cennso-website/issues/84","title":"Accessibility issue: Landmarks should have a unique role or role/label/title (i.e. accessible name) combination on /solutions"},"findings":[]},{"issue":{"state":"closed","id":3570939195,"nodeId":"I_kwDOQFxmOs7U2DU7","url":"https://github.com/cennso/cennso-website/issues/85","title":"Accessibility issue: Interactive controls must not be nested on /solutions"},"findings":[]},{"issue":{"state":"closed","id":3570939388,"nodeId":"I_kwDOQFxmOs7U2DX8","url":"https://github.com/cennso/cennso-website/issues/86","title":"Accessibility issue: All page content should be contained by landmarks on /solutions"},"findings":[]},{"findings":[{"scannerType":"axe","url":"https://cennso-website-5x2cyqza2-cennso.vercel.app","html":"<h1 class=\"font-bold text-3xl lg:text-5xl text-white\">Your mobile core deployed within 24 hours</h1>","problemShort":"elements must meet minimum color contrast ratio thresholds","problemUrl":"https://dequeuniversity.com/rules/axe/4.10/color-contrast?application=playwright","ruleId":"color-contrast","solutionShort":"ensure the contrast between foreground and background colors meets wcag 2 aa minimum contrast ratio thresholds","solutionLong":"Fix any of the following:\n  Element has insufficient color contrast of 2.64 (foreground color: #ffffff, background color: #36aadd, font size: 36.0pt (48px), font weight: bold). Expected contrast ratio of 3:1"}],"issue":{"state":"open","id":3571104202,"nodeId":"I_kwDOQFxmOs7U2rnK","url":"https://github.com/cennso/cennso-website/issues/88","title":"Accessibility issue: Elements must meet minimum color contrast ratio thresholds on /"}},{"findings":[{"scannerType":"axe","url":"https://cennso-website-5x2cyqza2-cennso.vercel.app","html":"<main class=\"flex-1 flex flex-col\" style=\"opacity:1;transform:none\">","problemShort":"main landmark should not be contained in another landmark","problemUrl":"https://dequeuniversity.com/rules/axe/4.10/landmark-main-is-top-level?application=playwright","ruleId":"landmark-main-is-top-level","solutionShort":"ensure the main landmark is at top level","solutionLong":"Fix any of the following:\n  The main landmark is contained in another landmark."}],"issue":{"state":"open","id":3571104382,"nodeId":"I_kwDOQFxmOs7U2rp-","url":"https://github.com/cennso/cennso-website/issues/89","title":"Accessibility issue: Main landmark should not be contained in another landmark on /"}},{"findings":[{"scannerType":"axe","url":"https://cennso-website-5x2cyqza2-cennso.vercel.app","html":"<main class=\"flex-1 flex flex-col z-10 bg-secondary-400\">","problemShort":"document should not have more than one main landmark","problemUrl":"https://dequeuniversity.com/rules/axe/4.10/landmark-no-duplicate-main?application=playwright","ruleId":"landmark-no-duplicate-main","solutionShort":"ensure the document has at most one main landmark","solutionLong":"Fix any of the following:\n  Document has more than one main landmark"}],"issue":{"state":"open","id":3571104579,"nodeId":"I_kwDOQFxmOs7U2rtD","url":"https://github.com/cennso/cennso-website/issues/90","title":"Accessibility issue: Document should not have more than one main landmark on /"}},{"findings":[{"scannerType":"axe","url":"https://cennso-website-5x2cyqza2-cennso.vercel.app","html":"<main class=\"flex-1 flex flex-col z-10 bg-secondary-400\">","problemShort":"landmarks should have a unique role or role/label/title (i.e. accessible name) combination","problemUrl":"https://dequeuniversity.com/rules/axe/4.10/landmark-unique?application=playwright","ruleId":"landmark-unique","solutionShort":"ensure landmarks are unique","solutionLong":"Fix any of the following:\n  The landmark must have a unique aria-label, aria-labelledby, or title to make landmarks distinguishable"}],"issue":{"state":"open","id":3571105068,"nodeId":"I_kwDOQFxmOs7U2r0s","url":"https://github.com/cennso/cennso-website/issues/91","title":"Accessibility issue: Landmarks should have a unique role or role/label/title (i.e. accessible name) combination on /"}},{"findings":[{"scannerType":"axe","url":"https://cennso-website-5x2cyqza2-cennso.vercel.app","html":"<button aria-expanded=\"false\" aria-haspopup=\"menu\" id=\":Rll36H2:\" class=\"block antialiased font-sans text-sm font-light leading-normal text-inherit p-0\">","problemShort":"interactive controls must not be nested","problemUrl":"https://dequeuniversity.com/rules/axe/4.10/nested-interactive?application=playwright","ruleId":"nested-interactive","solutionShort":"ensure interactive controls are not nested as they are not always announced by screen readers or can cause focus problems for assistive technologies","solutionLong":"Fix any of the following:\n  Element has focusable descendants"}],"issue":{"state":"open","id":3571105252,"nodeId":"I_kwDOQFxmOs7U2r3k","url":"https://github.com/cennso/cennso-website/issues/92","title":"Accessibility issue: Interactive controls must not be nested on /"}},{"findings":[{"scannerType":"axe","url":"https://cennso-website-5x2cyqza2-cennso.vercel.app","html":"<p class=\"flex flex-col items-end text-sm text-right\"><span class=\"md:py-1\">We use cookies for the best online experience.</span><a title=\"Privacy policy\" class=\"font-semibold text-secondary-200 underline hover:decoration-2\" target=\"_blank\" href=\"/privacy-policy\">Read our Privacy Policy</a></p>","problemShort":"all page content should be contained by landmarks","problemUrl":"https://dequeuniversity.com/rules/axe/4.10/region?application=playwright","ruleId":"region","solutionShort":"ensure all page content is contained by landmarks","solutionLong":"Fix any of the following:\n  Some page content is not contained by landmarks"}],"issue":{"state":"open","id":3571105444,"nodeId":"I_kwDOQFxmOs7U2r6k","url":"https://github.com/cennso/cennso-website/issues/93","title":"Accessibility issue: All page content should be contained by landmarks on /"}},{"findings":[{"scannerType":"axe","url":"https://cennso-website-5x2cyqza2-cennso.vercel.app/success-stories","html":"<h1 class=\"font-bold text-4xl lg:text-5xl text-white\">Success stories</h1>","problemShort":"elements must meet minimum color contrast ratio thresholds","problemUrl":"https://dequeuniversity.com/rules/axe/4.10/color-contrast?application=playwright","ruleId":"color-contrast","solutionShort":"ensure the contrast between foreground and background colors meets wcag 2 aa minimum contrast ratio thresholds","solutionLong":"Fix any of the following:\n  Element has insufficient color contrast of 2.64 (foreground color: #ffffff, background color: #36aadd, font size: 36.0pt (48px), font weight: bold). Expected contrast ratio of 3:1"}],"issue":{"state":"open","id":3571105635,"nodeId":"I_kwDOQFxmOs7U2r9j","url":"https://github.com/cennso/cennso-website/issues/94","title":"Accessibility issue: Elements must meet minimum color contrast ratio thresholds on /success-stories"}},{"findings":[{"scannerType":"axe","url":"https://cennso-website-5x2cyqza2-cennso.vercel.app/success-stories","html":"<h4 class=\"font-bold text-2xl text-secondary-200\">Cennso on Equinix Metal</h4>","problemShort":"heading levels should only increase by one","problemUrl":"https://dequeuniversity.com/rules/axe/4.10/heading-order?application=playwright","ruleId":"heading-order","solutionShort":"ensure the order of headings is semantically correct","solutionLong":"Fix any of the following:\n  Heading order invalid"}],"issue":{"state":"open","id":3571105811,"nodeId":"I_kwDOQFxmOs7U2sAT","url":"https://github.com/cennso/cennso-website/issues/95","title":"Accessibility issue: Heading levels should only increase by one on /success-stories"}},{"findings":[{"scannerType":"axe","url":"https://cennso-website-5x2cyqza2-cennso.vercel.app/success-stories","html":"<main class=\"flex-1 flex flex-col\" style=\"opacity:1;transform:none\">","problemShort":"main landmark should not be contained in another landmark","problemUrl":"https://dequeuniversity.com/rules/axe/4.10/landmark-main-is-top-level?application=playwright","ruleId":"landmark-main-is-top-level","solutionShort":"ensure the main landmark is at top level","solutionLong":"Fix any of the following:\n  The main landmark is contained in another landmark."}],"issue":{"state":"open","id":3571105998,"nodeId":"I_kwDOQFxmOs7U2sDO","url":"https://github.com/cennso/cennso-website/issues/96","title":"Accessibility issue: Main landmark should not be contained in another landmark on /success-stories"}},{"findings":[{"scannerType":"axe","url":"https://cennso-website-5x2cyqza2-cennso.vercel.app/success-stories","html":"<main class=\"flex-1 flex flex-col z-10 bg-secondary-400\">","problemShort":"document should not have more than one main landmark","problemUrl":"https://dequeuniversity.com/rules/axe/4.10/landmark-no-duplicate-main?application=playwright","ruleId":"landmark-no-duplicate-main","solutionShort":"ensure the document has at most one main landmark","solutionLong":"Fix any of the following:\n  Document has more than one main landmark"}],"issue":{"state":"open","id":3571106182,"nodeId":"I_kwDOQFxmOs7U2sGG","url":"https://github.com/cennso/cennso-website/issues/97","title":"Accessibility issue: Document should not have more than one main landmark on /success-stories"}},{"findings":[{"scannerType":"axe","url":"https://cennso-website-5x2cyqza2-cennso.vercel.app/success-stories","html":"<main class=\"flex-1 flex flex-col z-10 bg-secondary-400\">","problemShort":"landmarks should have a unique role or role/label/title (i.e. accessible name) combination","problemUrl":"https://dequeuniversity.com/rules/axe/4.10/landmark-unique?application=playwright","ruleId":"landmark-unique","solutionShort":"ensure landmarks are unique","solutionLong":"Fix any of the following:\n  The landmark must have a unique aria-label, aria-labelledby, or title to make landmarks distinguishable"}],"issue":{"state":"open","id":3571106379,"nodeId":"I_kwDOQFxmOs7U2sJL","url":"https://github.com/cennso/cennso-website/issues/98","title":"Accessibility issue: Landmarks should have a unique role or role/label/title (i.e. accessible name) combination on /success-stories"}},{"findings":[{"scannerType":"axe","url":"https://cennso-website-5x2cyqza2-cennso.vercel.app/success-stories","html":"<button aria-expanded=\"false\" aria-haspopup=\"menu\" id=\":Rll36H2:\" class=\"block antialiased font-sans text-sm font-light leading-normal text-inherit p-0\">","problemShort":"interactive controls must not be nested","problemUrl":"https://dequeuniversity.com/rules/axe/4.10/nested-interactive?application=playwright","ruleId":"nested-interactive","solutionShort":"ensure interactive controls are not nested as they are not always announced by screen readers or can cause focus problems for assistive technologies","solutionLong":"Fix any of the following:\n  Element has focusable descendants"}],"issue":{"state":"open","id":3571106576,"nodeId":"I_kwDOQFxmOs7U2sMQ","url":"https://github.com/cennso/cennso-website/issues/99","title":"Accessibility issue: Interactive controls must not be nested on /success-stories"}},{"findings":[{"scannerType":"axe","url":"https://cennso-website-5x2cyqza2-cennso.vercel.app/success-stories","html":"<p class=\"flex flex-col items-end text-sm text-right\"><span class=\"md:py-1\">We use cookies for the best online experience.</span><a title=\"Privacy policy\" class=\"font-semibold text-secondary-200 underline hover:decoration-2\" target=\"_blank\" href=\"/privacy-policy\">Read our Privacy Policy</a></p>","problemShort":"all page content should be contained by landmarks","problemUrl":"https://dequeuniversity.com/rules/axe/4.10/region?application=playwright","ruleId":"region","solutionShort":"ensure all page content is contained by landmarks","solutionLong":"Fix any of the following:\n  Some page content is not contained by landmarks"}],"issue":{"state":"open","id":3571106785,"nodeId":"I_kwDOQFxmOs7U2sPh","url":"https://github.com/cennso/cennso-website/issues/100","title":"Accessibility issue: All page content should be contained by landmarks on /success-stories"}},{"findings":[{"scannerType":"axe","url":"https://cennso-website-5x2cyqza2-cennso.vercel.app/contact","html":"<input name=\"privacy-policy\" id=\"privacy-policy\" required=\"\" type=\"checkbox\" class=\"sr-only w-4 h-6\" aria-hidden=\"true\">","problemShort":"aria hidden element must not be focusable or contain focusable elements","problemUrl":"https://dequeuniversity.com/rules/axe/4.10/aria-hidden-focus?application=playwright","ruleId":"aria-hidden-focus","solutionShort":"ensure aria-hidden elements are not focusable nor contain focusable elements","solutionLong":"Fix all of the following:\n  Focusable content should be disabled or be removed from the DOM"}],"issue":{"state":"open","id":3571106990,"nodeId":"I_kwDOQFxmOs7U2sSu","url":"https://github.com/cennso/cennso-website/issues/101","title":"Accessibility issue: Aria hidden element must not be focusable or contain focusable elements on /contact"}},{"findings":[{"scannerType":"axe","url":"https://cennso-website-5x2cyqza2-cennso.vercel.app/contact","html":"<input type=\"tel\" name=\"phone\" id=\"phone\" placeholder=\"Enter the phone number to which we will call you back\" autocomplete=\"phone\" class=\"block w-full rounded-md border-0 px-3.5 py-2 bg-[#ECF3F8] placeholder:text-gray-500 placeholder:font-light text-gray-800 shadow-sm ring-inset ring-gray-300 placeholder:text-gray-400 focus:ring-2 focus:ring-inset focus:ring-primary-600 sm:text-sm sm:leading-6 \">","problemShort":"autocomplete attribute must be used correctly","problemUrl":"https://dequeuniversity.com/rules/axe/4.10/autocomplete-valid?application=playwright","ruleId":"autocomplete-valid","solutionShort":"ensure the autocomplete attribute is correct and suitable for the form field","solutionLong":"Fix all of the following:\n  the autocomplete attribute is incorrectly formatted"}],"issue":{"state":"open","id":3571107159,"nodeId":"I_kwDOQFxmOs7U2sVX","url":"https://github.com/cennso/cennso-website/issues/102","title":"Accessibility issue: Autocomplete attribute must be used correctly on /contact"}},{"findings":[{"scannerType":"axe","url":"https://cennso-website-5x2cyqza2-cennso.vercel.app/contact","html":"<h1 class=\"font-bold text-4xl lg:text-5xl text-white\">Contact us</h1>","problemShort":"elements must meet minimum color contrast ratio thresholds","problemUrl":"https://dequeuniversity.com/rules/axe/4.10/color-contrast?application=playwright","ruleId":"color-contrast","solutionShort":"ensure the contrast between foreground and background colors meets wcag 2 aa minimum contrast ratio thresholds","solutionLong":"Fix any of the following:\n  Element has insufficient color contrast of 2.64 (foreground color: #ffffff, background color: #36aadd, font size: 36.0pt (48px), font weight: bold). Expected contrast ratio of 3:1"}],"issue":{"state":"open","id":3571107358,"nodeId":"I_kwDOQFxmOs7U2sYe","url":"https://github.com/cennso/cennso-website/issues/103","title":"Accessibility issue: Elements must meet minimum color contrast ratio thresholds on /contact"}},{"findings":[{"scannerType":"axe","url":"https://cennso-website-5x2cyqza2-cennso.vercel.app/contact","html":"<main class=\"flex-1 flex flex-col\" style=\"opacity:1;transform:none\">","problemShort":"main landmark should not be contained in another landmark","problemUrl":"https://dequeuniversity.com/rules/axe/4.10/landmark-main-is-top-level?application=playwright","ruleId":"landmark-main-is-top-level","solutionShort":"ensure the main landmark is at top level","solutionLong":"Fix any of the following:\n  The main landmark is contained in another landmark."}],"issue":{"state":"open","id":3571107546,"nodeId":"I_kwDOQFxmOs7U2sba","url":"https://github.com/cennso/cennso-website/issues/104","title":"Accessibility issue: Main landmark should not be contained in another landmark on /contact"}},{"findings":[{"scannerType":"axe","url":"https://cennso-website-5x2cyqza2-cennso.vercel.app/contact","html":"<main class=\"flex-1 flex flex-col z-10 bg-secondary-400\">","problemShort":"document should not have more than one main landmark","problemUrl":"https://dequeuniversity.com/rules/axe/4.10/landmark-no-duplicate-main?application=playwright","ruleId":"landmark-no-duplicate-main","solutionShort":"ensure the document has at most one main landmark","solutionLong":"Fix any of the following:\n  Document has more than one main landmark"}],"issue":{"state":"open","id":3571107732,"nodeId":"I_kwDOQFxmOs7U2seU","url":"https://github.com/cennso/cennso-website/issues/105","title":"Accessibility issue: Document should not have more than one main landmark on /contact"}},{"findings":[{"scannerType":"axe","url":"https://cennso-website-5x2cyqza2-cennso.vercel.app/contact","html":"<main class=\"flex-1 flex flex-col z-10 bg-secondary-400\">","problemShort":"landmarks should have a unique role or role/label/title (i.e. accessible name) combination","problemUrl":"https://dequeuniversity.com/rules/axe/4.10/landmark-unique?application=playwright","ruleId":"landmark-unique","solutionShort":"ensure landmarks are unique","solutionLong":"Fix any of the following:\n  The landmark must have a unique aria-label, aria-labelledby, or title to make landmarks distinguishable"}],"issue":{"state":"open","id":3571107939,"nodeId":"I_kwDOQFxmOs7U2shj","url":"https://github.com/cennso/cennso-website/issues/106","title":"Accessibility issue: Landmarks should have a unique role or role/label/title (i.e. accessible name) combination on /contact"}},{"findings":[{"scannerType":"axe","url":"https://cennso-website-5x2cyqza2-cennso.vercel.app/contact","html":"<button aria-expanded=\"false\" aria-haspopup=\"menu\" id=\":Rll36H2:\" class=\"block antialiased font-sans text-sm font-light leading-normal text-inherit p-0\">","problemShort":"interactive controls must not be nested","problemUrl":"https://dequeuniversity.com/rules/axe/4.10/nested-interactive?application=playwright","ruleId":"nested-interactive","solutionShort":"ensure interactive controls are not nested as they are not always announced by screen readers or can cause focus problems for assistive technologies","solutionLong":"Fix any of the following:\n  Element has focusable descendants"}],"issue":{"state":"open","id":3571108136,"nodeId":"I_kwDOQFxmOs7U2sko","url":"https://github.com/cennso/cennso-website/issues/107","title":"Accessibility issue: Interactive controls must not be nested on /contact"}},{"findings":[{"scannerType":"axe","url":"https://cennso-website-5x2cyqza2-cennso.vercel.app/contact","html":"<p class=\"flex flex-col items-end text-sm text-right\"><span class=\"md:py-1\">We use cookies for the best online experience.</span><a title=\"Privacy policy\" class=\"font-semibold text-secondary-200 underline hover:decoration-2\" target=\"_blank\" href=\"/privacy-policy\">Read our Privacy Policy</a></p>","problemShort":"all page content should be contained by landmarks","problemUrl":"https://dequeuniversity.com/rules/axe/4.10/region?application=playwright","ruleId":"region","solutionShort":"ensure all page content is contained by landmarks","solutionLong":"Fix any of the following:\n  Some page content is not contained by landmarks"}],"issue":{"state":"open","id":3571108342,"nodeId":"I_kwDOQFxmOs7U2sn2","url":"https://github.com/cennso/cennso-website/issues/108","title":"Accessibility issue: All page content should be contained by landmarks on /contact"}},{"findings":[{"scannerType":"axe","url":"https://cennso-website-5x2cyqza2-cennso.vercel.app/about","html":"<h4 class=\"font-bold text-lg text-white border-b-[1px] pb-1 border-white\">Company</h4>","problemShort":"heading levels should only increase by one","problemUrl":"https://dequeuniversity.com/rules/axe/4.10/heading-order?application=playwright","ruleId":"heading-order","solutionShort":"ensure the order of headings is semantically correct","solutionLong":"Fix any of the following:\n  Heading order invalid"}],"issue":{"state":"open","id":3571108797,"nodeId":"I_kwDOQFxmOs7U2su9","url":"https://github.com/cennso/cennso-website/issues/109","title":"Accessibility issue: Heading levels should only increase by one on /about"}},{"findings":[{"scannerType":"axe","url":"https://cennso-website-5x2cyqza2-cennso.vercel.app/about","html":"<main class=\"flex-1 flex flex-col\" style=\"opacity:1;transform:none\">","problemShort":"main landmark should not be contained in another landmark","problemUrl":"https://dequeuniversity.com/rules/axe/4.10/landmark-main-is-top-level?application=playwright","ruleId":"landmark-main-is-top-level","solutionShort":"ensure the main landmark is at top level","solutionLong":"Fix any of the following:\n  The main landmark is contained in another landmark."}],"issue":{"state":"open","id":3571109029,"nodeId":"I_kwDOQFxmOs7U2syl","url":"https://github.com/cennso/cennso-website/issues/110","title":"Accessibility issue: Main landmark should not be contained in another landmark on /about"}},{"findings":[{"scannerType":"axe","url":"https://cennso-website-5x2cyqza2-cennso.vercel.app/about","html":"<main class=\"flex-1 flex flex-col z-10 bg-secondary-400\">","problemShort":"document should not have more than one main landmark","problemUrl":"https://dequeuniversity.com/rules/axe/4.10/landmark-no-duplicate-main?application=playwright","ruleId":"landmark-no-duplicate-main","solutionShort":"ensure the document has at most one main landmark","solutionLong":"Fix any of the following:\n  Document has more than one main landmark"}],"issue":{"state":"open","id":3571109220,"nodeId":"I_kwDOQFxmOs7U2s1k","url":"https://github.com/cennso/cennso-website/issues/111","title":"Accessibility issue: Document should not have more than one main landmark on /about"}},{"findings":[{"scannerType":"axe","url":"https://cennso-website-5x2cyqza2-cennso.vercel.app/about","html":"<main class=\"flex-1 flex flex-col z-10 bg-secondary-400\">","problemShort":"landmarks should have a unique role or role/label/title (i.e. accessible name) combination","problemUrl":"https://dequeuniversity.com/rules/axe/4.10/landmark-unique?application=playwright","ruleId":"landmark-unique","solutionShort":"ensure landmarks are unique","solutionLong":"Fix any of the following:\n  The landmark must have a unique aria-label, aria-labelledby, or title to make landmarks distinguishable"}],"issue":{"state":"open","id":3571109415,"nodeId":"I_kwDOQFxmOs7U2s4n","url":"https://github.com/cennso/cennso-website/issues/112","title":"Accessibility issue: Landmarks should have a unique role or role/label/title (i.e. accessible name) combination on /about"}},{"findings":[{"scannerType":"axe","url":"https://cennso-website-5x2cyqza2-cennso.vercel.app/about","html":"<button aria-expanded=\"false\" aria-haspopup=\"menu\" id=\":Rll36H2:\" class=\"block antialiased font-sans text-sm font-light leading-normal text-inherit p-0\">","problemShort":"interactive controls must not be nested","problemUrl":"https://dequeuniversity.com/rules/axe/4.10/nested-interactive?application=playwright","ruleId":"nested-interactive","solutionShort":"ensure interactive controls are not nested as they are not always announced by screen readers or can cause focus problems for assistive technologies","solutionLong":"Fix any of the following:\n  Element has focusable descendants"}],"issue":{"state":"open","id":3571109605,"nodeId":"I_kwDOQFxmOs7U2s7l","url":"https://github.com/cennso/cennso-website/issues/113","title":"Accessibility issue: Interactive controls must not be nested on /about"}},{"findings":[{"scannerType":"axe","url":"https://cennso-website-5x2cyqza2-cennso.vercel.app/about","html":"<p class=\"flex flex-col items-end text-sm text-right\"><span class=\"md:py-1\">We use cookies for the best online experience.</span><a title=\"Privacy policy\" class=\"font-semibold text-secondary-200 underline hover:decoration-2\" target=\"_blank\" href=\"/privacy-policy\">Read our Privacy Policy</a></p>","problemShort":"all page content should be contained by landmarks","problemUrl":"https://dequeuniversity.com/rules/axe/4.10/region?application=playwright","ruleId":"region","solutionShort":"ensure all page content is contained by landmarks","solutionLong":"Fix any of the following:\n  Some page content is not contained by landmarks"}],"issue":{"state":"open","id":3571109787,"nodeId":"I_kwDOQFxmOs7U2s-b","url":"https://github.com/cennso/cennso-website/issues/114","title":"Accessibility issue: All page content should be contained by landmarks on /about"}},{"findings":[{"scannerType":"axe","url":"https://cennso-website-5x2cyqza2-cennso.vercel.app/blog","html":"<h4 class=\"font-bold text-lg text-white border-b-[1px] pb-1 border-white\">Company</h4>","problemShort":"heading levels should only increase by one","problemUrl":"https://dequeuniversity.com/rules/axe/4.10/heading-order?application=playwright","ruleId":"heading-order","solutionShort":"ensure the order of headings is semantically correct","solutionLong":"Fix any of the following:\n  Heading order invalid"}],"issue":{"state":"open","id":3571109969,"nodeId":"I_kwDOQFxmOs7U2tBR","url":"https://github.com/cennso/cennso-website/issues/115","title":"Accessibility issue: Heading levels should only increase by one on /blog"}},{"findings":[{"scannerType":"axe","url":"https://cennso-website-5x2cyqza2-cennso.vercel.app/blog","html":"<main class=\"flex-1 flex flex-col\" style=\"opacity:1;transform:none\">","problemShort":"main landmark should not be contained in another landmark","problemUrl":"https://dequeuniversity.com/rules/axe/4.10/landmark-main-is-top-level?application=playwright","ruleId":"landmark-main-is-top-level","solutionShort":"ensure the main landmark is at top level","solutionLong":"Fix any of the following:\n  The main landmark is contained in another landmark."}],"issue":{"state":"open","id":3571110161,"nodeId":"I_kwDOQFxmOs7U2tER","url":"https://github.com/cennso/cennso-website/issues/116","title":"Accessibility issue: Main landmark should not be contained in another landmark on /blog"}},{"findings":[{"scannerType":"axe","url":"https://cennso-website-5x2cyqza2-cennso.vercel.app/blog","html":"<main class=\"flex-1 flex flex-col z-10 bg-secondary-400\">","problemShort":"document should not have more than one main landmark","problemUrl":"https://dequeuniversity.com/rules/axe/4.10/landmark-no-duplicate-main?application=playwright","ruleId":"landmark-no-duplicate-main","solutionShort":"ensure the document has at most one main landmark","solutionLong":"Fix any of the following:\n  Document has more than one main landmark"}],"issue":{"state":"open","id":3571110536,"nodeId":"I_kwDOQFxmOs7U2tKI","url":"https://github.com/cennso/cennso-website/issues/117","title":"Accessibility issue: Document should not have more than one main landmark on /blog"}},{"findings":[{"scannerType":"axe","url":"https://cennso-website-5x2cyqza2-cennso.vercel.app/blog","html":"<main class=\"flex-1 flex flex-col z-10 bg-secondary-400\">","problemShort":"landmarks should have a unique role or role/label/title (i.e. accessible name) combination","problemUrl":"https://dequeuniversity.com/rules/axe/4.10/landmark-unique?application=playwright","ruleId":"landmark-unique","solutionShort":"ensure landmarks are unique","solutionLong":"Fix any of the following:\n  The landmark must have a unique aria-label, aria-labelledby, or title to make landmarks distinguishable"}],"issue":{"state":"open","id":3571110735,"nodeId":"I_kwDOQFxmOs7U2tNP","url":"https://github.com/cennso/cennso-website/issues/118","title":"Accessibility issue: Landmarks should have a unique role or role/label/title (i.e. accessible name) combination on /blog"}},{"findings":[{"scannerType":"axe","url":"https://cennso-website-5x2cyqza2-cennso.vercel.app/blog","html":"<button aria-expanded=\"false\" aria-haspopup=\"menu\" id=\":Rll36H2:\" class=\"block antialiased font-sans text-sm font-light leading-normal text-inherit p-0\">","problemShort":"interactive controls must not be nested","problemUrl":"https://dequeuniversity.com/rules/axe/4.10/nested-interactive?application=playwright","ruleId":"nested-interactive","solutionShort":"ensure interactive controls are not nested as they are not always announced by screen readers or can cause focus problems for assistive technologies","solutionLong":"Fix any of the following:\n  Element has focusable descendants"}],"issue":{"state":"open","id":3571110927,"nodeId":"I_kwDOQFxmOs7U2tQP","url":"https://github.com/cennso/cennso-website/issues/119","title":"Accessibility issue: Interactive controls must not be nested on /blog"}},{"findings":[{"scannerType":"axe","url":"https://cennso-website-5x2cyqza2-cennso.vercel.app/blog","html":"<p class=\"flex flex-col items-end text-sm text-right\"><span class=\"md:py-1\">We use cookies for the best online experience.</span><a title=\"Privacy policy\" class=\"font-semibold text-secondary-200 underline hover:decoration-2\" target=\"_blank\" href=\"/privacy-policy\">Read our Privacy Policy</a></p>","problemShort":"all page content should be contained by landmarks","problemUrl":"https://dequeuniversity.com/rules/axe/4.10/region?application=playwright","ruleId":"region","solutionShort":"ensure all page content is contained by landmarks","solutionLong":"Fix any of the following:\n  Some page content is not contained by landmarks"}],"issue":{"state":"open","id":3571111099,"nodeId":"I_kwDOQFxmOs7U2tS7","url":"https://github.com/cennso/cennso-website/issues/120","title":"Accessibility issue: All page content should be contained by landmarks on /blog"}},{"findings":[{"scannerType":"axe","url":"https://cennso-website-5x2cyqza2-cennso.vercel.app/solutions","html":"<h4 class=\"font-bold text-lg text-white border-b-[1px] pb-1 border-white\">Company</h4>","problemShort":"heading levels should only increase by one","problemUrl":"https://dequeuniversity.com/rules/axe/4.10/heading-order?application=playwright","ruleId":"heading-order","solutionShort":"ensure the order of headings is semantically correct","solutionLong":"Fix any of the following:\n  Heading order invalid"}],"issue":{"state":"open","id":3571111272,"nodeId":"I_kwDOQFxmOs7U2tVo","url":"https://github.com/cennso/cennso-website/issues/121","title":"Accessibility issue: Heading levels should only increase by one on /solutions"}},{"findings":[{"scannerType":"axe","url":"https://cennso-website-5x2cyqza2-cennso.vercel.app/solutions","html":"<main class=\"flex-1 flex flex-col\" style=\"opacity:1;transform:none\">","problemShort":"main landmark should not be contained in another landmark","problemUrl":"https://dequeuniversity.com/rules/axe/4.10/landmark-main-is-top-level?application=playwright","ruleId":"landmark-main-is-top-level","solutionShort":"ensure the main landmark is at top level","solutionLong":"Fix any of the following:\n  The main landmark is contained in another landmark."}],"issue":{"state":"open","id":3571111460,"nodeId":"I_kwDOQFxmOs7U2tYk","url":"https://github.com/cennso/cennso-website/issues/122","title":"Accessibility issue: Main landmark should not be contained in another landmark on /solutions"}},{"findings":[{"scannerType":"axe","url":"https://cennso-website-5x2cyqza2-cennso.vercel.app/solutions","html":"<main class=\"flex-1 flex flex-col z-10 bg-secondary-400\">","problemShort":"document should not have more than one main landmark","problemUrl":"https://dequeuniversity.com/rules/axe/4.10/landmark-no-duplicate-main?application=playwright","ruleId":"landmark-no-duplicate-main","solutionShort":"ensure the document has at most one main landmark","solutionLong":"Fix any of the following:\n  Document has more than one main landmark"}],"issue":{"state":"open","id":3571111646,"nodeId":"I_kwDOQFxmOs7U2tbe","url":"https://github.com/cennso/cennso-website/issues/123","title":"Accessibility issue: Document should not have more than one main landmark on /solutions"}},{"findings":[{"scannerType":"axe","url":"https://cennso-website-5x2cyqza2-cennso.vercel.app/solutions","html":"<main class=\"flex-1 flex flex-col z-10 bg-secondary-400\">","problemShort":"landmarks should have a unique role or role/label/title (i.e. accessible name) combination","problemUrl":"https://dequeuniversity.com/rules/axe/4.10/landmark-unique?application=playwright","ruleId":"landmark-unique","solutionShort":"ensure landmarks are unique","solutionLong":"Fix any of the following:\n  The landmark must have a unique aria-label, aria-labelledby, or title to make landmarks distinguishable"}],"issue":{"state":"open","id":3571111827,"nodeId":"I_kwDOQFxmOs7U2teT","url":"https://github.com/cennso/cennso-website/issues/124","title":"Accessibility issue: Landmarks should have a unique role or role/label/title (i.e. accessible name) combination on /solutions"}},{"findings":[{"scannerType":"axe","url":"https://cennso-website-5x2cyqza2-cennso.vercel.app/solutions","html":"<button aria-expanded=\"false\" aria-haspopup=\"menu\" id=\":Rll36H2:\" class=\"block antialiased font-sans text-sm font-light leading-normal text-inherit p-0\">","problemShort":"interactive controls must not be nested","problemUrl":"https://dequeuniversity.com/rules/axe/4.10/nested-interactive?application=playwright","ruleId":"nested-interactive","solutionShort":"ensure interactive controls are not nested as they are not always announced by screen readers or can cause focus problems for assistive technologies","solutionLong":"Fix any of the following:\n  Element has focusable descendants"}],"issue":{"state":"open","id":3571112019,"nodeId":"I_kwDOQFxmOs7U2thT","url":"https://github.com/cennso/cennso-website/issues/125","title":"Accessibility issue: Interactive controls must not be nested on /solutions"}},{"findings":[{"scannerType":"axe","url":"https://cennso-website-5x2cyqza2-cennso.vercel.app/solutions","html":"<p class=\"flex flex-col items-end text-sm text-right\"><span class=\"md:py-1\">We use cookies for the best online experience.</span><a title=\"Privacy policy\" class=\"font-semibold text-secondary-200 underline hover:decoration-2\" target=\"_blank\" href=\"/privacy-policy\">Read our Privacy Policy</a></p>","problemShort":"all page content should be contained by landmarks","problemUrl":"https://dequeuniversity.com/rules/axe/4.10/region?application=playwright","ruleId":"region","solutionShort":"ensure all page content is contained by landmarks","solutionLong":"Fix any of the following:\n  Some page content is not contained by landmarks"}],"issue":{"state":"open","id":3571112208,"nodeId":"I_kwDOQFxmOs7U2tkQ","url":"https://github.com/cennso/cennso-website/issues/126","title":"Accessibility issue: All page content should be contained by landmarks on /solutions"}}]
